django_fridgeblock-0.5.0.dist-info/DESCRIPTION.rst
django_fridgeblock-0.5.0.dist-info/METADATA
django_fridgeblock-0.5.0.dist-info/RECORD
django_fridgeblock-0.5.0.dist-info/WHEEL
django_fridgeblock-0.5.0.dist-info/metadata.json
django_fridgeblock-0.5.0.dist-info/top_level.txt
fridgeblock/__init__.py
fridgeblock/models.py
fridgeblock/urls.py
fridgeblock/views.py
