Metadata-Version: 2.0
Name: django-fridgeblock
Version: 0.5.0
Summary: Refrigerator Game PageBlock
Home-page: UNKNOWN
Author: Anders Pearson
Author-email: anders@columbia.edu
License: BSD
Platform: any
